csgame/__init__.py
csgame/camera.py
csgame/colour.py
csgame/menu.py
csgame/player.py
csgame-0.2.1.dist-info/LICENSE
csgame-0.2.1.dist-info/METADATA
csgame-0.2.1.dist-info/WHEEL
csgame-0.2.1.dist-info/top_level.txt
csgame-0.2.1.dist-info/RECORD
