Metadata-Version: 2.1
Name: csgame
Version: 0.2.1
Summary: useful tools for pygame development
Home-page: https://github.com/costott/csgame
Author: C Stott
Author-email: connorbstott@gmail.com
Classifier: Programming Language :: Python :: 3
Classifier: License :: OSI Approved :: MIT License
Classifier: Operating System :: OS Independent
Requires-Python: >3.0
License-File: LICENSE
